{"nodes": [{"id": "action_tiles", "label": "action-tiles.ts", "file_type": "code", "source_file": "C:\\Dev\\LuminaDeck\\packages\\shared\\src\\action-tiles.ts", "source_location": "L1"}, {"id": "action_tiles_gettilesbycategory", "label": "getTilesByCategory()", "file_type": "code", "source_file": "C:\\Dev\\LuminaDeck\\packages\\shared\\src\\action-tiles.ts", "source_location": "L497"}, {"id": "action_tiles_gettilebyid", "label": "getTileById()", "file_type": "code", "source_file": "C:\\Dev\\LuminaDeck\\packages\\shared\\src\\action-tiles.ts", "source_location": "L501"}, {"id": "action_tiles_searchtiles", "label": "searchTiles()", "file_type": "code", "source_file": "C:\\Dev\\LuminaDeck\\packages\\shared\\src\\action-tiles.ts", "source_location": "L505"}], "edges": [{"source": "action_tiles", "target": "types", "relation": "imports_from", "confidence": "EXTRACTED", "source_file": "C:\\Dev\\LuminaDeck\\packages\\shared\\src\\action-tiles.ts", "source_location": "L6", "weight": 1.0}, {"source": "action_tiles", "target": "action_tiles_gettilesbycategory", "relation": "contains", "confidence": "EXTRACTED", "source_file": "C:\\Dev\\LuminaDeck\\packages\\shared\\src\\action-tiles.ts", "source_location": "L497", "weight": 1.0}, {"source": "action_tiles", "target": "action_tiles_gettilebyid", "relation": "contains", "confidence": "EXTRACTED", "source_file": "C:\\Dev\\LuminaDeck\\packages\\shared\\src\\action-tiles.ts", "source_location": "L501", "weight": 1.0}, {"source": "action_tiles", "target": "action_tiles_searchtiles", "relation": "contains", "confidence": "EXTRACTED", "source_file": "C:\\Dev\\LuminaDeck\\packages\\shared\\src\\action-tiles.ts", "source_location": "L505", "weight": 1.0}]}