{"nodes": [{"id": "mod", "label": "mod.rs", "file_type": "code", "source_file": "C:\\Dev\\LuminaDeck\\apps\\companion\\src-tauri\\src\\actions\\mod.rs", "source_location": "L1"}, {"id": "mod_action", "label": "Action", "file_type": "code", "source_file": "C:\\Dev\\LuminaDeck\\apps\\companion\\src-tauri\\src\\actions\\mod.rs", "source_location": "L11"}, {"id": "mod_actionerror", "label": "ActionError", "file_type": "code", "source_file": "C:\\Dev\\LuminaDeck\\apps\\companion\\src-tauri\\src\\actions\\mod.rs", "source_location": "L46"}, {"id": "mod_execute_action", "label": "execute_action()", "file_type": "code", "source_file": "C:\\Dev\\LuminaDeck\\apps\\companion\\src-tauri\\src\\actions\\mod.rs", "source_location": "L76"}], "edges": [{"source": "mod", "target": "deserialize", "relation": "imports_from", "confidence": "EXTRACTED", "source_file": "C:\\Dev\\LuminaDeck\\apps\\companion\\src-tauri\\src\\actions\\mod.rs", "source_location": "L6", "weight": 1.0}, {"source": "mod", "target": "error", "relation": "imports_from", "confidence": "EXTRACTED", "source_file": "C:\\Dev\\LuminaDeck\\apps\\companion\\src-tauri\\src\\actions\\mod.rs", "source_location": "L7", "weight": 1.0}, {"source": "mod", "target": "mod_action", "relation": "contains", "confidence": "EXTRACTED", "source_file": "C:\\Dev\\LuminaDeck\\apps\\companion\\src-tauri\\src\\actions\\mod.rs", "source_location": "L11", "weight": 1.0}, {"source": "mod", "target": "mod_actionerror", "relation": "contains", "confidence": "EXTRACTED", "source_file": "C:\\Dev\\LuminaDeck\\apps\\companion\\src-tauri\\src\\actions\\mod.rs", "source_location": "L46", "weight": 1.0}, {"source": "mod", "target": "mod_execute_action", "relation": "contains", "confidence": "EXTRACTED", "source_file": "C:\\Dev\\LuminaDeck\\apps\\companion\\src-tauri\\src\\actions\\mod.rs", "source_location": "L76", "weight": 1.0}]}